dotscience/__init__.py
dotscience/_version.py
dotscience/test_dotscience.py
dotscience-0.6.2.dist-info/LICENSE
dotscience-0.6.2.dist-info/METADATA
dotscience-0.6.2.dist-info/WHEEL
dotscience-0.6.2.dist-info/top_level.txt
dotscience-0.6.2.dist-info/zip-safe
dotscience-0.6.2.dist-info/RECORD
