Metadata-Version: 2.1
Name: dotscience
Version: 0.6.2
Summary: Tools for writing Dotscience workloads
Home-page: https://github.com/dotmesh-io/dotscience-python
Author: Subtree, Inc
Author-email: support@dotscience.com
License: UNKNOWN
Platform: UNKNOWN
Classifier: Programming Language :: Python :: 3
Classifier: License :: OSI Approved :: Apache Software License
Classifier: Operating System :: OS Independent
Requires-Dist: jsonrpcclient[requests]
Requires-Dist: requests
Requires-Dist: datadots-api (>=0.2.1)
